{
  "type": "content",
  "index": 4,
  "title": "The studio loop is local",
  "eyebrow": "Operating model",
  "summary": "slideotter treats deck authoring as a local application workflow backed by explicit files and server-owned mutations.",
  "signalsTitle": "Loop stages",
  "guardrailsTitle": "Boundaries",
  "signals": [
    {
      "id": "signal-plan",
      "title": "Plan",
      "body": "Capture objective, outline, tone, and constraints."
    },
    {
      "id": "signal-edit",
      "title": "Edit",
      "body": "Change text and JSON against the live slide."
    },
    {
      "id": "signal-review",
      "title": "Review",
      "body": "Compare candidates before promotion."
    },
    {
      "id": "signal-ship",
      "title": "Ship",
      "body": "Build, validate, and archive."
    }
  ],
  "guardrails": [
    {
      "id": "guardrail-local",
      "title": "Repo-local",
      "body": "No remote service required for local rules."
    },
    {
      "id": "guardrail-server",
      "title": "Server-owned writes",
      "body": "The browser requests changes."
    },
    {
      "id": "guardrail-inspect",
      "title": "Inspectable state",
      "body": "Files stay readable."
    }
  ]
}
