{
  "eyebrow": "Harvesting Logistics",
  "guardrails": [
    {
      "body": "Always verify species identification before harvesting during any season.",
      "id": "the-foraging-calendar-guardrail-1",
      "title": "Safety Priority"
    },
    {
      "body": "Check local regulations regarding foraging limits in protected areas.",
      "id": "the-foraging-calendar-guardrail-2",
      "title": "Regulatory Compliance"
    },
    {
      "body": "Use a timeline graphic to visualize the July to October",
      "id": "the-foraging-calendar-guardrail-3",
      "title": "Visual Reference"
    }
  ],
  "guardrailsTitle": "Operational Constraints",
  "layout": "steps",
  "signals": [
    {
      "body": "Early summer brings the first wave of highly sought-after species.",
      "id": "the-foraging-calendar-signal-1",
      "title": "Mid-Summer Peak"
    },
    {
      "body": "Late summer and autumn offer the highest volume of diverse",
      "id": "the-foraging-calendar-signal-2",
      "title": "Autumn Expansion"
    },
    {
      "body": "Frosts in late October signal the end of the primary",
      "id": "the-foraging-calendar-signal-3",
      "title": "Season Conclusion"
    },
    {
      "body": "Monitor local weather patterns to predict specific fruiting windows.",
      "id": "the-foraging-calendar-signal-4",
      "title": "Strategic Timing"
    }
  ],
  "signalsTitle": "Seasonal Windows",
  "summary": "A strategic overview of the peak months for mushroom availability in Finland, spanning",
  "title": "The Foraging Calendar",
  "type": "content",
  "index": 16
}
